CHANGES.rst
CONTRIBUTORS.rst
DEVELOP.rst
LICENSE.GPL
LICENSE.rst
MANIFEST.in
README.rst
constraints.txt
constraints_plone51.txt
constraints_plone52.txt
requirements.txt
setup.cfg
setup.py
docs/index.rst
src/rt/__init__.py
src/rt.categorysupport.egg-info/PKG-INFO
src/rt.categorysupport.egg-info/SOURCES.txt
src/rt.categorysupport.egg-info/dependency_links.txt
src/rt.categorysupport.egg-info/entry_points.txt
src/rt.categorysupport.egg-info/namespace_packages.txt
src/rt.categorysupport.egg-info/not-zip-safe
src/rt.categorysupport.egg-info/requires.txt
src/rt.categorysupport.egg-info/top_level.txt
src/rt/categorysupport/__init__.py
src/rt/categorysupport/configure.zcml
src/rt/categorysupport/indexer.py
src/rt/categorysupport/interfaces.py
src/rt/categorysupport/permissions.zcml
src/rt/categorysupport/setuphandlers.py
src/rt/categorysupport/testing.py
src/rt/categorysupport/upgrades.py
src/rt/categorysupport/upgrades.zcml
src/rt/categorysupport/vocabularies.py
src/rt/categorysupport/behaviors/__init__.py
src/rt/categorysupport/behaviors/category.py
src/rt/categorysupport/behaviors/configure.zcml
src/rt/categorysupport/browser/__init__.py
src/rt/categorysupport/browser/configure.zcml
src/rt/categorysupport/browser/settings.py
src/rt/categorysupport/browser/view.py
src/rt/categorysupport/browser/overrides/.gitkeep
src/rt/categorysupport/browser/static/.gitkeep
src/rt/categorysupport/browser/templates/keywords.pt
src/rt/categorysupport/browser/templates/taxonomy_info.pt
src/rt/categorysupport/locales/rt.categorysupport.pot
src/rt/categorysupport/locales/update.sh
src/rt/categorysupport/locales/it/LC_MESSAGES/rt.categorysupport.po
src/rt/categorysupport/profiles/default/browserlayer.xml
src/rt/categorysupport/profiles/default/catalog.xml
src/rt/categorysupport/profiles/default/controlpanel.xml
src/rt/categorysupport/profiles/default/metadata.xml
src/rt/categorysupport/profiles/default/registry.xml
src/rt/categorysupport/profiles/default/rolemap.xml
src/rt/categorysupport/profiles/default/types.xml
src/rt/categorysupport/profiles/default/types/Folder.xml
src/rt/categorysupport/profiles/uninstall/browserlayer.xml
src/rt/categorysupport/tests/__init__.py
src/rt/categorysupport/tests/test_robot.py
src/rt/categorysupport/tests/test_setup.py
src/rt/categorysupport/tests/test_view.py
src/rt/categorysupport/tests/robot/test_example.robot